LICENSE.txt
README.md
setup.py
text_equivalences/__init__.py
text_equivalences/decorators.py
text_equivalences/graph.py
text_equivalences/transducer.py
text_equivalences.egg-info/PKG-INFO
text_equivalences.egg-info/SOURCES.txt
text_equivalences.egg-info/dependency_links.txt
text_equivalences.egg-info/top_level.txt